echr_extractor/ECHR_html_downloader.py
echr_extractor/ECHR_metadata_harvester.py
echr_extractor/ECHR_nodes_edges_list_transform.py
echr_extractor/__init__.py
echr_extractor/clean_ref.py
echr_extractor/cli.py
echr_extractor/echr.py
echr_extractor/testing_file.py
echr_extractor-1.0.46.dist-info/licenses/LICENSE
echr_extractor-1.0.46.dist-info/METADATA
echr_extractor-1.0.46.dist-info/WHEEL
echr_extractor-1.0.46.dist-info/entry_points.txt
echr_extractor-1.0.46.dist-info/top_level.txt
echr_extractor-1.0.46.dist-info/RECORD
