Metadata-Version: 2.4
Name: echr-extractor
Version: 1.0.46
Summary: Python library for extracting case law data from the European Court of Human Rights (ECHR) HUDOC database
Author-email: LawTech Lab <lawtech@maastrichtuniversity.nl>
License: Apache-2.0
Project-URL: Homepage, https://github.com/maastrichtlawtech/echr-extractor
Project-URL: Repository, https://github.com/maastrichtlawtech/echr-extractor
Project-URL: Bug Reports, https://github.com/maastrichtlawtech/echr-extractor/issues
Project-URL: Documentation, https://github.com/maastrichtlawtech/echr-extractor
Keywords: echr,extractor,european,convention,human,rights,court,case-law,legal,hudoc,data-extraction
Classifier: Development Status :: 4 - Beta
Classifier: Intended Audience :: Developers
Classifier: Intended Audience :: Legal Industry
Classifier: Intended Audience :: Science/Research
Classifier: License :: OSI Approved :: Apache Software License
Classifier: Operating System :: OS Independent
Classifier: Programming Language :: Python :: 3
Classifier: Programming Language :: Python :: 3.8
Classifier: Programming Language :: Python :: 3.9
Classifier: Programming Language :: Python :: 3.10
Classifier: Programming Language :: Python :: 3.11
Classifier: Topic :: Scientific/Engineering :: Information Analysis
Classifier: Topic :: Software Development :: Libraries :: Python Modules
Classifier: Topic :: Text Processing :: Markup :: HTML
Requires-Python: >=3.8
License-File: LICENSE
Requires-Dist: requests>=2.26.0
Requires-Dist: pandas>=1.3.0
Requires-Dist: beautifulsoup4>=4.9.3
Requires-Dist: dateparser>=1.0.0
Requires-Dist: tqdm>=4.60.0
Provides-Extra: dev
Requires-Dist: pytest>=6.0; extra == "dev"
Requires-Dist: pytest-cov>=2.10; extra == "dev"
Requires-Dist: black>=21.0.0; extra == "dev"
Requires-Dist: isort>=5.0.0; extra == "dev"
Requires-Dist: flake8>=3.8.0; extra == "dev"
Requires-Dist: mypy>=0.910; extra == "dev"
Provides-Extra: docs
Requires-Dist: sphinx>=4.0.0; extra == "docs"
Requires-Dist: sphinx-rtd-theme>=0.5.0; extra == "docs"
Dynamic: license-file
